COPYING.txt
MANIFEST.in
README.md
package_variables.py
requirements.txt
setup.py
localmaxfilter/__init__.py
localmaxfilter/localmaxfilter_plugin.py
localmaxfilter/core/__init__.py
localmaxfilter/core/local_max_filter.py
localmaxfilter/images/lmf_logo.png
localmaxfilter/interfaces/__init__.py
localmaxfilter/interfaces/exports.py
localmaxfilter/interfaces/imports.py
localmaxfilter/interfaces/local_max_filter.ui
localmaxfilter/interfaces/local_max_filter_cli.py
localmaxfilter/interfaces/local_max_filter_gui.py
localmaxfilter/interfaces/localmaxfilter_processing.py
localmaxfilter/interfaces/localmaxfilter_provider.py
treedensitycalculator.egg-info/PKG-INFO
treedensitycalculator.egg-info/SOURCES.txt
treedensitycalculator.egg-info/dependency_links.txt
treedensitycalculator.egg-info/entry_points.txt
treedensitycalculator.egg-info/top_level.txt