Metadata-Version: 2.1
Name: treedensitycalculator
Version: 1.5.7
Summary: The Tree Density Calculator is a QGIS plugin and command line interface package designed to calculate tree densities based on brightness images, using the local maximum in a sliding window.
Home-page: https://bitbucket.org/kul-reseco/localmaxfilter
Author: Ann Crabbé
Author-email: acrabbe.foss@gmail.com
License: UNKNOWN
Project-URL: Documentation, https://treedensitycalculator.readthedocs.io
Project-URL: Source Code, https://bitbucket.org/kul-reseco/localmaxfilter/src
Project-URL: Issue Tracker, https://bitbucket.org/kul-reseco/localmaxfilter/issues
Keywords: forestry,tree density,remote sensing,sliding window,local maxima
Platform: UNKNOWN
